{"css":"","framework":"duck-10.0.0","title":"Ajuda TextEdit","build_id":"5748ce99680ce2c540716594","icon":"..\/SharedGlobalArt\/AppIconDefault_TextEdit.png","sections":{"txte66378667":{"name":"Crear i obrir documents","children":["txtee6663a0e","txte51413d09","txte71fa0102","txted0b6cd61","txte825e96e7"]},"txtead825d1d":{"name":"Donar format al documents","children":["txte313927e3","txte88fd8bcb","txte3ab65427","txte44f15043","txte5c41b552"]},"txte33f64074":{"name":"Editar documents","children":["txte58c1b39e","txte15912956","txte4120841e","txtec0fe94d2","txte5d6611d0","txte52183e41"]},"txteff27d864":{"name":"Utilitzar eines d’escriptura","children":["txte86b1c1b9","txtef6cfde1a","txtef5d9dd70"]}},"birdseed_version":5,"toc":["txte036c41fb","txte66378667","txtead825d1d","txte33f64074","txteff27d864"],"locale":"ca","version":"10.12","enable_tracking":false,"source_schema":"apd-schema","platform":"mac","build_date":"2016.05.27-16:36:50","landing":"txted35466","product":"textedit","urls":{},"copyright":"","show_previous_next":false,"topics":{"txte5c41b552":{"name":"Configurar l’espaiat entre caràcters i línies","searchName":"Ajustar l’espai entre caràcters i l’interlineat a TextEdit"},"txtec0fe94d2":{"name":"Inserir caràcters especials","searchName":"Inserir caràcters especials a documents de TextEdit"},"txtee6663a0e":{"name":"Iniciar un document nou","searchName":"Iniciar documents nous de TextEdit"},"txtef6cfde1a":{"name":"Buscar i substituir text","searchName":"Buscar i substituir text a TextEdit"},"txte44f15043":{"name":"Afegir capçaleres i peus de pàgina","searchName":"Afegir capçaleres i peus de pàgina a TextEdit"},"txte71fa0102":{"name":"Desar un document","searchName":"Desar documents de TextEdit"},"txte825e96e7":{"name":"Escoltar la lectura d’un document en veu alta","searchName":"Escoltar documents de TextEdit"},"txte313927e3":{"name":"Ajustar els marges i els paràgrafs","searchName":"Ajustar els marges i els paràgrafs a TextEdit"},"txte51413d09":{"name":"Obrir un document","searchName":"Obrir documents a TextEdit"},"txte4120841e":{"name":"Afegir taules i llistes","searchName":"Afegir taules i llistes a un document de TextEdit"},"txte5d6611d0":{"name":"Afegir fotos, pel·lícules i arxius","searchName":"Afegir fotos, pel·lícules i arxius a TextEdit"},"txte52183e41":{"name":"Anotar imatges","searchName":"Anotar imatges amb marques a TextEdit"},"txted1019":{"name":"Si desapareix el format del text","searchName":"Si desapareix el format del text a TextEdit"},"txtef5d9dd70":{"name":"Completar paraules escrites parcialment","searchName":"Completar paraules escrites parcialment a TextEdit"},"txted1026":{"name":"Fer que els documents siguin només de lectura","searchName":"Fer que els documents de TextEdit siguin només de lectura"},"txted1028":{"name":"Si els caràcters no es mostren correctament","searchName":"Si els caràcters no es mostren correctament a TextEdit"},"txted1063":{"name":"Definir les preferències de documents nous, d’obrir i de desar de TextEdit","searchName":"Definir les preferències de documents nous, d’obrir i de desar a TextEdit"},"txte036c41fb":{"name":"Visió general del TextEdit"},"txted0b6cd61":{"name":"Treballar amb documents HTML","searchName":"Treballar amb documents HTML a TextEdit"},"txte88fd8bcb":{"name":"Inserir salts de línia, salts de paràgraf i salts de pàgina","searchName":"Inserir salts de línia, salts de paràgraf i salts de pàgina a TextEdit"},"txted35466":{"name":"Ajuda TextEdit","href":"txted35466.html","categories":["landing"]},"txte3ab65427":{"name":"Canviar com s’ajusta el text","searchName":"Canviar com s’ajusta el text a TextEdit"},"txte86b1c1b9":{"name":"Revisar l’ortografia i la gramàtica","searchName":"Revisar l’ortografia i la gramàtica a TextEdit"},"txted11519":{"name":"Saltar a ubicacions en documents","searchName":"Saltar a ubicacions en documents de TextEdit"},"txted35481":{"name":"Utilitzar text vertical","searchName":"Utilitzar text vertical a TextEdit"},"txted35741":{"name":"Veure les directives RTF d’arxius RTF","searchName":"Veure les directives RTF d’arxius RTF utilitzant TextEdit"},"txte58c1b39e":{"name":"Canviar l’aspecte del text","searchName":"Canviar l’aspecte del text als documents de TextEdit"},"txted35745":{"name":"Afegir enllaços clicables automàticament","searchName":"Afegir automàticament enllaços clicables als documents de TextEdit"},"txted35753":{"name":"Activar detectors de dades","searchName":"Activar detectors de dades a TextEdit"},"txte15912956":{"name":"Utilitzar estils","searchName":"Utilitzar estils als documents de TextEdit"},"txted35754":{"name":"Espaiar correctament el text enganxat automàticament","searchName":"Espaiar correctament el text enganxat automàticament a TextEdit"}},"copyright_text":"© 2016 Apple Inc. Tots els drets reservats."}